<?xml version="1.0" encoding="UTF-8" standalone="no"?><lyc:root xmlns:lyc="JLyc.Development@gmail.com">
    <lyc:commands>
        <lyc:command lyc:id="email" lyc:modifier="1">

            <lyc:executor>cmd</lyc:executor>
            <lyc:parameter>-c</lyc:parameter>
            <lyc:code>start http://mail.google.com</lyc:code>
        </lyc:command>
        <lyc:command lyc:id="email" lyc:modifier="0">
            <lyc:executor>cmd</lyc:executor>
            <lyc:parameter>/c</lyc:parameter>
            <lyc:code>start http://mail.google.com</lyc:code>
        </lyc:command>
        <lyc:command lyc:id="face book" lyc:modifier="1">
            <lyc:executor>cmd</lyc:executor>
            <lyc:parameter>/c</lyc:parameter>
            <lyc:code>start http://mail.google.com</lyc:code>
        </lyc:command>
        <lyc:command lyc:id="note pad" lyc:modifier="1">
            <lyc:executor>cmd</lyc:executor>
            <lyc:parameter>/c</lyc:parameter>
            <lyc:code>notepad.exe</lyc:code>
        </lyc:command>
        <lyc:command lyc:id="note pad" lyc:modifier="0">
            <lyc:executor>cmd</lyc:executor>
            <lyc:parameter>/-c</lyc:parameter>
            <lyc:executor>taskkill /F /IM notepad.exe</lyc:executor>
        </lyc:command>
    </lyc:commands>
</lyc:root>